[
    {"no":"1","id":"lotno","columnname":"ﾛｯﾄNo","type":"String","format":""},
    {"no":"2","id":"kaisuu","columnname":"回数","type":"Integer","format":"9,0"},
    {"no":"3","id":"kcpno","columnname":"KCPNO","type":"String","format":""},
    {"no":"4","id":"tokuisaki","columnname":"客先","type":"String","format":""},
    {"no":"5","id":"ownercode","columnname":"ｵｰﾅｰ","type":"String","format":""},
    {"no":"6","id":"lotkubuncode","columnname":"ﾛｯﾄ区分","type":"String","format":""},
    {"no":"7","id":"siteikousa","columnname":"指定公差","type":"String","format":""},
    {"no":"8","id":"atokouteisijinaiyou","columnname":"後工程指示内容","type":"String","format":""},
    {"no":"9","id":"okuriryouhinsuu","columnname":"送り良品数","type":"Integer","format":"9,0"},
    {"no":"10","id":"ukeiretannijyuryo","columnname":"受入れ単位重量","type":"BigDecimal","format":"2,4"},
    {"no":"11","id":"ukeiresoujyuryou","columnname":"受入れ総重量","type":"BigDecimal","format":"8,2"},
    {"no":"12","id":"gdyakitukenitiji","columnname":"外部電極焼付日時","type":"timestamp","format":"yyyy/MM/dd HH:mm:ss"},
    {"no":"13","id":"mekkinitiji","columnname":"ﾒｯｷ日時","type":"timestamp","format":"yyyy/MM/dd HH:mm:ss"},
    {"no":"14","id":"kensabasyo","columnname":"検査場所","type":"String","format":""},
    {"no":"15","id":"senbetukaisinitiji","columnname":"選別開始日時","type":"timestamp","format":"yyyy/MM/dd HH:mm:ss"},
    {"no":"16","id":"senbetusyuryounitiji","columnname":"選別終了日時","type":"timestamp","format":"yyyy/MM/dd HH:mm:ss"},
    {"no":"17","id":"kensagouki","columnname":"検査号機","type":"String","format":""},
    {"no":"18","id":"bunruiairatu","columnname":"分類ｴｱｰ圧","type":"BigDecimal","format":"5,2"},
    {"no":"19","id":"cdcontactatu","columnname":"CDｺﾝﾀｸﾄ圧","type":"Integer","format":"9,0"},
    {"no":"20","id":"ircontactatu","columnname":"IRｺﾝﾀｸﾄ圧","type":"Integer","format":"9,0"},
    {"no":"21","id":"stationcd1","columnname":"使用後ｽﾃｰｼｮﾝ確認CD1","type":"Integer","format":"9,0"},
    {"no":"22","id":"stationpc1","columnname":"使用後ｽﾃｰｼｮﾝ確認PC1","type":"Integer","format":"9,0"},
    {"no":"23","id":"stationpc2","columnname":"使用後ｽﾃｰｼｮﾝ確認PC2","type":"Integer","format":"9,0"},
    {"no":"24","id":"stationpc3","columnname":"使用後ｽﾃｰｼｮﾝ確認PC3","type":"Integer","format":"9,0"},
    {"no":"25","id":"stationpc4","columnname":"使用後ｽﾃｰｼｮﾝ確認PC4","type":"Integer","format":"9,0"},
    {"no":"26","id":"stationir1","columnname":"使用後ｽﾃｰｼｮﾝ確認IR1","type":"Integer","format":"9,0"},
    {"no":"27","id":"stationir2","columnname":"使用後ｽﾃｰｼｮﾝ確認IR2","type":"Integer","format":"9,0"},
    {"no":"28","id":"stationir3","columnname":"使用後ｽﾃｰｼｮﾝ確認IR3","type":"Integer","format":"9,0"},
    {"no":"29","id":"stationir4","columnname":"使用後ｽﾃｰｼｮﾝ確認IR4","type":"Integer","format":"9,0"},
    {"no":"30","id":"stationir5","columnname":"使用後ｽﾃｰｼｮﾝ確認IR5","type":"Integer","format":"9,0"},
    {"no":"31","id":"stationir6","columnname":"使用後ｽﾃｰｼｮﾝ確認IR6","type":"Integer","format":"9,0"},
    {"no":"32","id":"stationir7","columnname":"使用後ｽﾃｰｼｮﾝ確認IR7","type":"Integer","format":"9,0"},
    {"no":"33","id":"stationir8","columnname":"使用後ｽﾃｰｼｮﾝ確認IR8","type":"Integer","format":"9,0"},
    {"no":"34","id":"koteidenkyoku","columnname":"固定電極 外観･段差","type":"String","format":""},
    {"no":"35","id":"torakkugaido","columnname":"ﾄﾗｯｸｶﾞｲﾄﾞ隙間","type":"String","format":""},
    {"no":"36","id":"testplatekeijo","columnname":"ﾃｽﾄﾌﾟﾚｰﾄ 形状･清掃","type":"String","format":""},
    {"no":"37","id":"bunruifukidasi","columnname":"分類吹き出し穴","type":"String","format":""},
    {"no":"38","id":"testplatekakunin","columnname":"ﾃｽﾄﾌﾟﾚｰﾄ位置確認(穴位置)","type":"String","format":""},
    {"no":"39","id":"denkyokuseisou","columnname":"電極清掃･動作","type":"String","format":""},
    {"no":"40","id":"senbetujunjo","columnname":"選別順序変更","type":"String","format":""},
    {"no":"41","id":"setteikakunin","columnname":"設定ﾓｰﾄﾞ確認","type":"String","format":""},
    {"no":"42","id":"haisenkakunin","columnname":"配線確認","type":"String","format":""},
    {"no":"43","id":"seihintounyuujotai","columnname":"製品投入状態","type":"String","format":""},
    {"no":"44","id":"binboxseisoucheck","columnname":"BINﾎﾞｯｸｽ内の清掃ﾁｪｯｸ","type":"String","format":""},
    {"no":"45","id":"setsya","columnname":"ｾｯﾄ者","type":"String","format":""},
    {"no":"46","id":"kakuninsya","columnname":"確認者","type":"String","format":""},
    {"no":"47","id":"siteikousabudomari1","columnname":"指定公差歩留まり1","type":"String","format":""},
    {"no":"48","id":"siteikousabudomari2","columnname":"指定公差歩留まり2","type":"String","format":""},
    {"no":"49","id":"siteikousabudomari3","columnname":"指定公差歩留まり3","type":"String","format":""},
    {"no":"50","id":"testplatekanrino","columnname":"ﾃｽﾄﾌﾟﾚｰﾄ管理No","type":"String","format":""},
    {"no":"51","id":"tan","columnname":"Tanδ","type":"BigDecimal","format":"4,1"},
    {"no":"52","id":"sokuteisyuhasuu","columnname":"測定周波数","type":"String","format":""},
    {"no":"53","id":"sokuteidenatu","columnname":"測定電圧","type":"BigDecimal","format":"2,1"},
    {"no":"54","id":"douhinsyu","columnname":"同品種","type":"Integer","format":"11,0"},
    {"no":"55","id":"hoseiyoutippuyoryou","columnname":"補正用ﾁｯﾌﾟ容量","type":"BigDecimal","format":"9,5"},
    {"no":"56","id":"hoseiyoutipputan","columnname":"補正用ﾁｯﾌﾟTanδ","type":"BigDecimal","format":"9,5"},
    {"no":"57","id":"hoseimae","columnname":"補正前","type":"BigDecimal","format":"9,5"},
    {"no":"58","id":"hoseigo","columnname":"補正後","type":"BigDecimal","format":"9,5"},
    {"no":"59","id":"hoseiritu","columnname":"補正率","type":"BigDecimal","format":"5,2"},
    {"no":"60","id":"standard","columnname":"ｽﾀﾝﾀﾞｰﾄﾞ補正","type":"String","format":""},
    {"no":"61","id":"bunruikakunin","columnname":"分類確認","type":"String","format":""},
    {"no":"62","id":"gaikankakunin","columnname":"外観確認","type":"String","format":""},
    {"no":"63","id":"netsusyorinitiji","columnname":"熱処理日時","type":"timestamp","format":"yyyy/MM/dd HH:mm:ss"},
    {"no":"64","id":"agingjikan","columnname":"ｴｰｼﾞﾝｸﾞ時間","type":"BigDecimal","format":"5,2"},
    {"no":"65","id":"jutenritu","columnname":"充填率","type":"String","format":""},
    {"no":"66","id":"mc","columnname":"MC","type":"String","format":""},
    {"no":"67","id":"kyoseihaisyutu","columnname":"強制排出","type":"String","format":""},
    {"no":"68","id":"rakka","columnname":"落下","type":"String","format":""},
    {"no":"69","id":"syoninsha","columnname":"承認者","type":"String","format":""},
    {"no":"70","id":"furimukesya","columnname":"振向者","type":"String","format":""},
    {"no":"71","id":"bikou1","columnname":"備考1","type":"String","format":""},
    {"no":"72","id":"bikou2","columnname":"備考2","type":"String","format":""},
    {"no":"73","id":"pcdenatu1","columnname":"ﾌﾟﾘﾁｬｰｼﾞ条件 PC① 電圧","type":"BigDecimal","format":"5,1"},
    {"no":"74","id":"pcjudenjikan1","columnname":"ﾌﾟﾘﾁｬｰｼﾞ条件 PC① 充電時間","type":"Integer","format":"9,0"},
    {"no":"75","id":"pcdenatu2","columnname":"ﾌﾟﾘﾁｬｰｼﾞ条件 PC② 電圧","type":"BigDecimal","format":"5,1"},
    {"no":"76","id":"pcjudenjikan2","columnname":"ﾌﾟﾘﾁｬｰｼﾞ条件 PC② 充電時間","type":"Integer","format":"9,0"},
    {"no":"77","id":"pcdenatu3","columnname":"ﾌﾟﾘﾁｬｰｼﾞ条件 PC③ 電圧","type":"BigDecimal","format":"5,1"},
    {"no":"78","id":"pcjudenjikan3","columnname":"ﾌﾟﾘﾁｬｰｼﾞ条件 PC③ 充電時間","type":"Integer","format":"9,0"},
    {"no":"79","id":"pcdenatu4","columnname":"ﾌﾟﾘﾁｬｰｼﾞ条件 PC④ 電圧","type":"BigDecimal","format":"5,1"},
    {"no":"80","id":"pcjudenjikan4","columnname":"ﾌﾟﾘﾁｬｰｼﾞ条件 PC④ 充電時間","type":"Integer","format":"9,0"},
    {"no":"81","id":"irdenatu1","columnname":"耐電圧設定条件 IR① 電圧","type":"BigDecimal","format":"5,1"},
    {"no":"82","id":"irhanteiti1low","columnname":"耐電圧設定条件 IR① 判定値(低)","type":"BigDecimal","format":"14,12"},
    {"no":"83","id":"irhanteiti1","columnname":"耐電圧設定条件 IR① 判定値","type":"BigDecimal","format":"14,12"},
    {"no":"84","id":"irhanteiti1tani","columnname":"耐電圧設定条件 IR① 判定値 単位","type":"String","format":""},
    {"no":"85","id":"irjudenjikan1","columnname":"耐電圧設定条件 IR① 充電時間","type":"Integer","format":"9,0"},
    {"no":"86","id":"irdenatu2","columnname":"耐電圧設定条件 IR② 電圧","type":"BigDecimal","format":"5,1"},
    {"no":"87","id":"irhanteiti2low","columnname":"耐電圧設定条件 IR② 判定値(低)","type":"BigDecimal","format":"14,12"},
    {"no":"88","id":"irhanteiti2","columnname":"耐電圧設定条件 IR② 判定値","type":"BigDecimal","format":"14,12"},
    {"no":"89","id":"irhanteiti2tani","columnname":"耐電圧設定条件 IR② 判定値 単位","type":"String","format":""},
    {"no":"90","id":"irjudenjikan2","columnname":"耐電圧設定条件 IR② 充電時間","type":"Integer","format":"9,0"},
    {"no":"91","id":"irdenatu3","columnname":"耐電圧設定条件 IR③ 電圧","type":"BigDecimal","format":"5,1"},
    {"no":"92","id":"irhanteiti3low","columnname":"耐電圧設定条件 IR③ 判定値(低)","type":"BigDecimal","format":"14,12"},
    {"no":"93","id":"irhanteiti3","columnname":"耐電圧設定条件 IR③ 判定値","type":"BigDecimal","format":"14,12"},
    {"no":"94","id":"irhanteiti3tani","columnname":"耐電圧設定条件 IR③ 判定値 単位","type":"String","format":""},
    {"no":"95","id":"irjudenjikan3","columnname":"耐電圧設定条件 IR③ 充電時間","type":"Integer","format":"9,0"},
    {"no":"96","id":"irdenatu4","columnname":"耐電圧設定条件 IR④ 電圧","type":"BigDecimal","format":"5,1"},
    {"no":"97","id":"irhanteiti4low","columnname":"耐電圧設定条件 IR④ 判定値(低)","type":"BigDecimal","format":"14,12"},
    {"no":"98","id":"irhanteiti4","columnname":"耐電圧設定条件 IR④ 判定値","type":"BigDecimal","format":"14,12"},
    {"no":"99","id":"irhanteiti4tani","columnname":"耐電圧設定条件 IR④ 判定値 単位","type":"String","format":""},
    {"no":"100","id":"irjudenjikan4","columnname":"耐電圧設定条件 IR④ 充電時間","type":"Integer","format":"9,0"},
    {"no":"101","id":"irdenatu5","columnname":"耐電圧設定条件 IR⑤ 電圧","type":"BigDecimal","format":"5,1"},
    {"no":"102","id":"irhanteiti5low","columnname":"耐電圧設定条件 IR⑤ 判定値(低)","type":"BigDecimal","format":"14,12"},
    {"no":"103","id":"irhanteiti5","columnname":"耐電圧設定条件 IR⑤ 判定値","type":"BigDecimal","format":"14,12"},
    {"no":"104","id":"irhanteiti5tani","columnname":"耐電圧設定条件 IR⑤ 判定値 単位","type":"String","format":""},
    {"no":"105","id":"irjudenjikan5","columnname":"耐電圧設定条件 IR⑤ 充電時間","type":"Integer","format":"9,0"},
    {"no":"106","id":"irdenatu6","columnname":"耐電圧設定条件 IR⑥ 電圧","type":"BigDecimal","format":"5,1"},
    {"no":"107","id":"irhanteiti6low","columnname":"耐電圧設定条件 IR⑥ 判定値(低)","type":"BigDecimal","format":"14,12"},
    {"no":"108","id":"irhanteiti6","columnname":"耐電圧設定条件 IR⑥ 判定値","type":"BigDecimal","format":"14,12"},
    {"no":"109","id":"irhanteiti6tani","columnname":"耐電圧設定条件 IR⑥ 判定値 単位","type":"String","format":""},
    {"no":"110","id":"irjudenjikan6","columnname":"耐電圧設定条件 IR⑥ 充電時間","type":"Integer","format":"9,0"},
    {"no":"111","id":"irdenatu7","columnname":"耐電圧設定条件 IR⑦ 電圧","type":"BigDecimal","format":"5,1"},
    {"no":"112","id":"irhanteiti7low","columnname":"耐電圧設定条件 IR⑦ 判定値(低)","type":"BigDecimal","format":"14,12"},
    {"no":"113","id":"irhanteiti7","columnname":"耐電圧設定条件 IR⑦ 判定値","type":"BigDecimal","format":"14,12"},
    {"no":"114","id":"irhanteiti7tani","columnname":"耐電圧設定条件 IR⑦ 判定値 単位","type":"String","format":""},
    {"no":"115","id":"irjudenjikan7","columnname":"耐電圧設定条件 IR⑦ 充電時間","type":"Integer","format":"9,0"},
    {"no":"116","id":"irdenatu8","columnname":"耐電圧設定条件 IR⑧ 電圧","type":"BigDecimal","format":"5,1"},
    {"no":"117","id":"irhanteiti8low","columnname":"耐電圧設定条件 IR⑧ 判定値(低)","type":"BigDecimal","format":"14,12"},
    {"no":"118","id":"irhanteiti8","columnname":"耐電圧設定条件 IR⑧ 判定値","type":"BigDecimal","format":"14,12"},
    {"no":"119","id":"irhanteiti8tani","columnname":"耐電圧設定条件 IR⑧ 判定値 単位","type":"String","format":""},
    {"no":"120","id":"irjudenjikan8","columnname":"耐電圧設定条件 IR⑧ 充電時間","type":"Integer","format":"9,0"},
    {"no":"121","id":"rdcrange1","columnname":"RDC1 ﾚﾝｼﾞ","type":"BigDecimal","format":"5,1"},
    {"no":"122","id":"rdchantei1","columnname":"RDC1 判定値","type":"BigDecimal","format":"5,1"},
    {"no":"123","id":"rdcrange2","columnname":"RDC2 ﾚﾝｼﾞ","type":"BigDecimal","format":"5,1"},
    {"no":"124","id":"rdchantei2","columnname":"RDC2 判定値","type":"BigDecimal","format":"5,1"},
    {"no":"125","id":"drop13pc","columnname":"DROP1,3 PC","type":"BigDecimal","format":"5,1"},
    {"no":"126","id":"drop13ps","columnname":"DROP1,3 PS","type":"BigDecimal","format":"5,1"},
    {"no":"127","id":"drop13msdc","columnname":"DROP1,3 MS･DC","type":"BigDecimal","format":"5,1"},
    {"no":"128","id":"drop24pc","columnname":"DROP2,4 PC","type":"BigDecimal","format":"5,1"},
    {"no":"129","id":"drop24ps","columnname":"DROP2,4 PS","type":"BigDecimal","format":"5,1"},
    {"no":"130","id":"drop24msdc","columnname":"DROP2,4 MS･DC","type":"BigDecimal","format":"5,1"},
    {"no":"131","id":"bin1setteiti","columnname":"BIN1 %区分(設定値)","type":"String","format":""},
    {"no":"132","id":"bin1senbetukubun","columnname":"BIN1 選別区分","type":"String","format":""},
    {"no":"133","id":"bin1keiryougosuryou","columnname":"BIN1 計量後数量","type":"Integer","format":"9,0"},
    {"no":"134","id":"bin1countersuu","columnname":"BIN1 ｶｳﾝﾀｰ数","type":"Integer","format":"9,0"},
    {"no":"135","id":"bin1gosaritu","columnname":"BIN1 誤差率(%)","type":"BigDecimal","format":"5,2"},
    {"no":"136","id":"bin1masinfuryouritu","columnname":"BIN1 ﾏｼﾝ不良率(%)","type":"BigDecimal","format":"7,4"},
    {"no":"137","id":"bin1nukitorikekkabosuu","columnname":"BIN1 抜き取り結果(子数)","type":"Integer","format":"9,0"},
    {"no":"138","id":"bin1nukitorikekka","columnname":"BIN1 抜き取り結果(母数)","type":"Integer","format":"9,0"},
    {"no":"139","id":"bin1sinnofuryouritu","columnname":"BIN1 真の不良率(%)","type":"BigDecimal","format":"7,4"},
    {"no":"140","id":"bin1kekkacheck","columnname":"BIN1 結果ﾁｪｯｸ","type":"String","format":""},
    {"no":"141","id":"bin1fukurocheck","columnname":"BIN1 袋ﾁｪｯｸ","type":"Integer","format":"9,0"},
    {"no":"142","id":"bin2setteiti","columnname":"BIN2 %区分(設定値)","type":"String","format":""},
    {"no":"143","id":"bin2senbetukubun","columnname":"BIN2 選別区分","type":"String","format":""},
    {"no":"144","id":"bin2keiryougosuryou","columnname":"BIN2 計量後数量","type":"Integer","format":"9,0"},
    {"no":"145","id":"bin2countersuu","columnname":"BIN2 ｶｳﾝﾀｰ数","type":"Integer","format":"9,0"},
    {"no":"146","id":"bin2gosaritu","columnname":"BIN2 誤差率(%)","type":"BigDecimal","format":"5,2"},
    {"no":"147","id":"bin2masinfuryouritu","columnname":"BIN2 ﾏｼﾝ不良率(%)","type":"BigDecimal","format":"7,4"},
    {"no":"148","id":"bin2nukitorikekkabosuu","columnname":"BIN2 抜き取り結果(子数)","type":"Integer","format":"9,0"},
    {"no":"149","id":"bin2nukitorikekka","columnname":"BIN2 抜き取り結果(母数)","type":"Integer","format":"9,0"},
    {"no":"150","id":"bin2sinnofuryouritu","columnname":"BIN2 真の不良率(%)","type":"BigDecimal","format":"7,4"},
    {"no":"151","id":"bin2kekkacheck","columnname":"BIN2 結果ﾁｪｯｸ","type":"String","format":""},
    {"no":"152","id":"bin2fukurocheck","columnname":"BIN2 袋ﾁｪｯｸ","type":"Integer","format":"9,0"},
    {"no":"153","id":"bin3setteiti","columnname":"BIN3 %区分(設定値)","type":"String","format":""},
    {"no":"154","id":"bin3senbetukubun","columnname":"BIN3 選別区分","type":"String","format":""},
    {"no":"155","id":"bin3keiryougosuryou","columnname":"BIN3 計量後数量","type":"Integer","format":"9,0"},
    {"no":"156","id":"bin3countersuu","columnname":"BIN3 ｶｳﾝﾀｰ数","type":"Integer","format":"9,0"},
    {"no":"157","id":"bin3gosaritu","columnname":"BIN3 誤差率(%)","type":"BigDecimal","format":"5,2"},
    {"no":"158","id":"bin3masinfuryouritu","columnname":"BIN3 ﾏｼﾝ不良率(%)","type":"BigDecimal","format":"7,4"},
    {"no":"159","id":"bin3nukitorikekkabosuu","columnname":"BIN3 抜き取り結果(子数)","type":"Integer","format":"9,0"},
    {"no":"160","id":"bin3nukitorikekka","columnname":"BIN3 抜き取り結果(母数)","type":"Integer","format":"9,0"},
    {"no":"161","id":"bin3sinnofuryouritu","columnname":"BIN3 真の不良率(%)","type":"BigDecimal","format":"7,4"},
    {"no":"162","id":"bin3kekkacheck","columnname":"BIN3 結果ﾁｪｯｸ","type":"String","format":""},
    {"no":"163","id":"bin3fukurocheck","columnname":"BIN3 袋ﾁｪｯｸ","type":"Integer","format":"9,0"},
    {"no":"164","id":"bin4setteiti","columnname":"BIN4 %区分(設定値)","type":"String","format":""},
    {"no":"165","id":"bin4senbetukubun","columnname":"BIN4 選別区分","type":"String","format":""},
    {"no":"166","id":"bin4keiryougosuryou","columnname":"BIN4 計量後数量","type":"Integer","format":"9,0"},
    {"no":"167","id":"bin4countersuu","columnname":"BIN4 ｶｳﾝﾀｰ数","type":"Integer","format":"9,0"},
    {"no":"168","id":"bin4gosaritu","columnname":"BIN4 誤差率(%)","type":"BigDecimal","format":"5,2"},
    {"no":"169","id":"bin4masinfuryouritu","columnname":"BIN4 ﾏｼﾝ不良率(%)","type":"BigDecimal","format":"7,4"},
    {"no":"170","id":"bin4nukitorikekkabosuu","columnname":"BIN4 抜き取り結果(子数)","type":"Integer","format":"9,0"},
    {"no":"171","id":"bin4nukitorikekka","columnname":"BIN4 抜き取り結果(母数)","type":"Integer","format":"9,0"},
    {"no":"172","id":"bin4sinnofuryouritu","columnname":"BIN4 真の不良率(%)","type":"BigDecimal","format":"7,4"},
    {"no":"173","id":"bin4kekkacheck","columnname":"BIN4 結果ﾁｪｯｸ","type":"String","format":""},
    {"no":"174","id":"bin4fukurocheck","columnname":"BIN4 袋ﾁｪｯｸ","type":"Integer","format":"9,0"},
    {"no":"175","id":"bin5setteiti","columnname":"BIN5 %区分(設定値)","type":"String","format":""},
    {"no":"176","id":"bin5senbetukubun","columnname":"BIN5 選別区分","type":"String","format":""},
    {"no":"177","id":"bin5keiryougosuryou","columnname":"BIN5 計量後数量","type":"Integer","format":"9,0"},
    {"no":"178","id":"bin5countersuu","columnname":"BIN5 ｶｳﾝﾀｰ数","type":"Integer","format":"9,0"},
    {"no":"179","id":"bin5gosaritu","columnname":"BIN5 誤差率(%)","type":"BigDecimal","format":"5,2"},
    {"no":"180","id":"bin5masinfuryouritu","columnname":"BIN5 ﾏｼﾝ不良率(%)","type":"BigDecimal","format":"7,4"},
    {"no":"181","id":"bin5nukitorikekkabosuu","columnname":"BIN5 抜き取り結果(子数)","type":"Integer","format":"9,0"},
    {"no":"182","id":"bin5nukitorikekka","columnname":"BIN5 抜き取り結果(母数)","type":"Integer","format":"9,0"},
    {"no":"183","id":"bin5sinnofuryouritu","columnname":"BIN5 真の不良率(%)","type":"BigDecimal","format":"7,4"},
    {"no":"184","id":"bin5kekkacheck","columnname":"BIN5 結果ﾁｪｯｸ","type":"String","format":""},
    {"no":"185","id":"bin5fukurocheck","columnname":"BIN5 袋ﾁｪｯｸ","type":"Integer","format":"9,0"},
    {"no":"186","id":"bin6setteiti","columnname":"BIN6 %区分(設定値)","type":"String","format":""},
    {"no":"187","id":"bin6senbetukubun","columnname":"BIN6 選別区分","type":"String","format":""},
    {"no":"188","id":"bin6keiryougosuryou","columnname":"BIN6 計量後数量","type":"Integer","format":"9,0"},
    {"no":"189","id":"bin6countersuu","columnname":"BIN6 ｶｳﾝﾀｰ数","type":"Integer","format":"9,0"},
    {"no":"190","id":"bin6gosaritu","columnname":"BIN6 誤差率(%)","type":"BigDecimal","format":"5,2"},
    {"no":"191","id":"bin6masinfuryouritu","columnname":"BIN6 ﾏｼﾝ不良率(%)","type":"BigDecimal","format":"7,4"},
    {"no":"192","id":"bin6nukitorikekkabosuu","columnname":"BIN6 抜き取り結果(子数)","type":"Integer","format":"9,0"},
    {"no":"193","id":"bin6nukitorikekka","columnname":"BIN6 抜き取り結果(母数)","type":"Integer","format":"9,0"},
    {"no":"194","id":"bin6sinnofuryouritu","columnname":"BIN6 真の不良率(%)","type":"BigDecimal","format":"7,4"},
    {"no":"195","id":"bin6kekkacheck","columnname":"BIN6 結果ﾁｪｯｸ","type":"String","format":""},
    {"no":"196","id":"bin6fukurocheck","columnname":"BIN6 袋ﾁｪｯｸ","type":"Integer","format":"9,0"},
    {"no":"197","id":"bin7setteiti","columnname":"BIN7 %区分(設定値)","type":"String","format":""},
    {"no":"198","id":"bin7senbetukubun","columnname":"BIN7 選別区分","type":"String","format":""},
    {"no":"199","id":"bin7keiryougosuryou","columnname":"BIN7 計量後数量","type":"Integer","format":"9,0"},
    {"no":"200","id":"bin7countersuu","columnname":"BIN7 ｶｳﾝﾀｰ数","type":"Integer","format":"9,0"},
    {"no":"201","id":"bin7gosaritu","columnname":"BIN7 誤差率(%)","type":"BigDecimal","format":"5,2"},
    {"no":"202","id":"bin7masinfuryouritu","columnname":"BIN7 ﾏｼﾝ不良率(%)","type":"BigDecimal","format":"7,4"},
    {"no":"203","id":"bin7nukitorikekkabosuu","columnname":"BIN7 抜き取り結果(子数)","type":"Integer","format":"9,0"},
    {"no":"204","id":"bin7nukitorikekka","columnname":"BIN7 抜き取り結果(母数)","type":"Integer","format":"9,0"},
    {"no":"205","id":"bin7sinnofuryouritu","columnname":"BIN7 真の不良率(%)","type":"BigDecimal","format":"7,4"},
    {"no":"206","id":"bin7kekkacheck","columnname":"BIN7 結果ﾁｪｯｸ","type":"String","format":""},
    {"no":"207","id":"bin7fukurocheck","columnname":"BIN7 袋ﾁｪｯｸ","type":"Integer","format":"9,0"},
    {"no":"208","id":"bin8setteiti","columnname":"BIN8 %区分(設定値)","type":"String","format":""},
    {"no":"209","id":"bin8senbetukubun","columnname":"BIN8 選別区分","type":"String","format":""},
    {"no":"210","id":"bin8keiryougosuryou","columnname":"BIN8 計量後数量","type":"Integer","format":"9,0"},
    {"no":"211","id":"bin8countersuu","columnname":"BIN8 ｶｳﾝﾀｰ数","type":"Integer","format":"9,0"},
    {"no":"212","id":"bin8gosaritu","columnname":"BIN8 誤差率(%)","type":"BigDecimal","format":"5,2"},
    {"no":"213","id":"bin8masinfuryouritu","columnname":"BIN8 ﾏｼﾝ不良率(%)","type":"BigDecimal","format":"7,4"},
    {"no":"214","id":"bin8nukitorikekkabosuu","columnname":"BIN8 抜き取り結果(子数)","type":"Integer","format":"9,0"},
    {"no":"215","id":"bin8nukitorikekka","columnname":"BIN8 抜き取り結果(母数)","type":"Integer","format":"9,0"},
    {"no":"216","id":"bin8sinnofuryouritu","columnname":"BIN8 真の不良率(%)","type":"BigDecimal","format":"7,4"},
    {"no":"217","id":"bin8kekkacheck","columnname":"BIN8 結果ﾁｪｯｸ","type":"String","format":""},
    {"no":"218","id":"bin8fukurocheck","columnname":"BIN8 袋ﾁｪｯｸ","type":"Integer","format":"9,0"},
    {"no":"219","id":"bin9keiryougosuryou","columnname":"BIN9 強制排出 計量後数量","type":"Integer","format":"9,0"},
    {"no":"220","id":"bin9masinfuryouritu","columnname":"BIN9 強制排出 ﾏｼﾝ不良率","type":"BigDecimal","format":"7,4"},
    {"no":"221","id":"rakkakeiryougosuryou","columnname":"落下 計量後数量","type":"Integer","format":"9,0"},
    {"no":"222","id":"rakkamasinfuryouritu","columnname":"落下 ﾏｼﾝ不良率","type":"BigDecimal","format":"7,4"},
    {"no":"223","id":"handasample","columnname":"半田ｻﾝﾌﾟﾙ","type":"String","format":""},
    {"no":"224","id":"sinraiseisample","columnname":"信頼性ｻﾝﾌﾟﾙ","type":"String","format":""},
    {"no":"225","id":"satsample","columnname":"SATｻﾝﾌﾟﾙ","type":"String","format":""},
    {"no":"226","id":"sinfuryouhanteisya","columnname":"真不良判定者","type":"String","format":""},
    {"no":"227","id":"hanteinyuuryokusya","columnname":"判定入力者","type":"String","format":""},
    {"no":"228","id":"toridasisya","columnname":"取出者","type":"String","format":""},
    {"no":"229","id":"kousa1","columnname":"公差①","type":"String","format":""},
    {"no":"230","id":"juryou1","columnname":"重量①","type":"BigDecimal","format":"6,2"},
    {"no":"231","id":"kosuu1","columnname":"個数①","type":"Integer","format":"9,0"},
    {"no":"232","id":"kousa2","columnname":"公差②","type":"String","format":""},
    {"no":"233","id":"juryou2","columnname":"重量②","type":"BigDecimal","format":"6,2"},
    {"no":"234","id":"kosuu2","columnname":"個数②","type":"Integer","format":"9,0"},
    {"no":"235","id":"kousa3","columnname":"公差③","type":"String","format":""},
    {"no":"236","id":"juryou3","columnname":"重量③","type":"BigDecimal","format":"6,2"},
    {"no":"237","id":"kosuu3","columnname":"個数③","type":"Integer","format":"9,0"},
    {"no":"238","id":"kousa4","columnname":"公差④","type":"String","format":""},
    {"no":"239","id":"juryou4","columnname":"重量④","type":"BigDecimal","format":"6,2"},
    {"no":"240","id":"kosuu4","columnname":"個数④","type":"Integer","format":"9,0"},
    {"no":"241","id":"countersousuu","columnname":"計量総数","type":"Integer","format":"9,0"},
    {"no":"242","id":"ryohinjuryou","columnname":"良品重量","type":"BigDecimal","format":"6,2"},
    {"no":"243","id":"ryohinkosuu","columnname":"良品個数","type":"Integer","format":"9,0"},
    {"no":"244","id":"budomari","columnname":"歩留まり","type":"BigDecimal","format":"5,2"},
    {"no":"245","id":"binkakuninsya","columnname":"BIN確認者","type":"String","format":""},
    {"no":"246","id":"saiken","columnname":"電気特性再検","type":"String","format":""},
    {"no":"247","id":"setubikubun","columnname":"設備区分","type":"String","format":""}
]